LICENSE
MANIFEST.in
README.rst
setup.py
bee_django_course_simple/__init__.py
bee_django_course_simple/admin.py
bee_django_course_simple/apis.py
bee_django_course_simple/apps.py
bee_django_course_simple/config.py
bee_django_course_simple/decorators.py
bee_django_course_simple/exports.py
bee_django_course_simple/forms.py
bee_django_course_simple/models.py
bee_django_course_simple/qiniu_api.py
bee_django_course_simple/signals.py
bee_django_course_simple/tests.py
bee_django_course_simple/urls.py
bee_django_course_simple/utils.py
bee_django_course_simple/views.py
bee_django_course_simple.egg-info/PKG-INFO
bee_django_course_simple.egg-info/SOURCES.txt
bee_django_course_simple.egg-info/dependency_links.txt
bee_django_course_simple.egg-info/requires.txt
bee_django_course_simple.egg-info/top_level.txt
bee_django_course_simple/migrations/0001_initial.py
bee_django_course_simple/migrations/0001_initial.pyc
bee_django_course_simple/migrations/0002_auto_20190416_1712.py
bee_django_course_simple/migrations/0002_auto_20190416_1712.pyc
bee_django_course_simple/migrations/0003_auto_20190416_1737.py
bee_django_course_simple/migrations/0003_auto_20190416_1737.pyc
bee_django_course_simple/migrations/0004_auto_20190417_1737.py
bee_django_course_simple/migrations/0004_auto_20190417_1737.pyc
bee_django_course_simple/migrations/0005_userimage.py
bee_django_course_simple/migrations/0005_userimage.pyc
bee_django_course_simple/migrations/0006_auto_20190418_1318.py
bee_django_course_simple/migrations/0006_auto_20190418_1318.pyc
bee_django_course_simple/migrations/0007_auto_20190418_1409.py
bee_django_course_simple/migrations/0007_auto_20190418_1409.pyc
bee_django_course_simple/migrations/0008_usersection_started_at.py
bee_django_course_simple/migrations/0008_usersection_started_at.pyc
bee_django_course_simple/migrations/0009_auto_20190421_1752.py
bee_django_course_simple/migrations/0009_auto_20190421_1752.pyc
bee_django_course_simple/migrations/0010_question_section.py
bee_django_course_simple/migrations/0010_question_section.pyc
bee_django_course_simple/migrations/0011_question_course.py
bee_django_course_simple/migrations/0011_question_course.pyc
bee_django_course_simple/migrations/0012_auto_20190421_1846.py
