Metadata-Version: 1.0
Name: bee-django-course-simple
Version: 0.0.29
Summary: A line of description
Home-page: UNKNOWN
Author: zhangyue
Author-email: zhangyue@zhenpuedu.com
License: MIT
Platform: UNKNOWN
